flextomo/__init__.py
flextomo/model.py
flextomo/phantom.py
flextomo/projector.py
flextomo-1.0.0.dist-info/LICENSE.md
flextomo-1.0.0.dist-info/METADATA
flextomo-1.0.0.dist-info/WHEEL
flextomo-1.0.0.dist-info/top_level.txt
flextomo-1.0.0.dist-info/RECORD
