Metadata-Version: 2.1
Name: flextomo
Version: 1.0.0
Summary: ASTRA-based cone beam tomography reconstructions.
Home-page: https://github.com/cicwi/flextomo
Author: Alex Kostenko
License: GNU General Public License v3
License-File: LICENSE.md
Requires-Dist: numpy
Requires-Dist: astra-toolbox>1.9.0
Requires-Dist: tqdm
Requires-Dist: scipy
Requires-Dist: flexdata
Provides-Extra: dev
Requires-Dist: sphinx; extra == "dev"
Requires-Dist: sphinx-rtd-theme; extra == "dev"
Requires-Dist: myst-parser; extra == "dev"
